bytedance_account_tech/__init__.py
bytedance_account_tech-0.0.1.dist-info/METADATA
bytedance_account_tech-0.0.1.dist-info/WHEEL
bytedance_account_tech-0.0.1.dist-info/top_level.txt
bytedance_account_tech-0.0.1.dist-info/RECORD
