Metadata-Version: 2.1
Name: bytedance-account-tech
Version: 0.0.1
Summary: A simple package named bytedance_account_tech
Home-page: https://github.com/artifact/bytedance_account_tech.git
Author: artifact
Author-email: artifact@example.com
License: UNKNOWN
Platform: UNKNOWN
Classifier: Programming Language :: Python :: 3
Classifier: License :: OSI Approved :: MIT License
Classifier: Operating System :: OS Independent
